beaker_util/__init__.py
beaker_util/launch_interactive.py
beaker_util/main.py
beaker_util/monitor.py
beaker_util/utils.py
beakerutil-0.3.10.dist-info/licenses/LICENSE
beakerutil-0.3.10.dist-info/METADATA
beakerutil-0.3.10.dist-info/WHEEL
beakerutil-0.3.10.dist-info/entry_points.txt
beakerutil-0.3.10.dist-info/top_level.txt
beakerutil-0.3.10.dist-info/RECORD
