Metadata-Version: 2.4
Name: BeakerUtil
Version: 0.3.10
Summary: Command-line tool for beaker utilities
Home-page: https://github.com/abhaybd/BeakerUtil
Author: Abhay Deshpande
Author-email: abhayd@allenai.org
License: MIT
Project-URL: Bug Reports, https://github.com/abhaybd/BeakerUtil/issues
Project-URL: Source, https://github.com/abhaybd/BeakerUtil
Project-URL: Documentation, https://github.com/abhaybd/BeakerUtil#readme
Classifier: Development Status :: 4 - Beta
Classifier: Intended Audience :: Developers
Classifier: License :: OSI Approved :: MIT License
Classifier: Programming Language :: Python :: 3
Classifier: Operating System :: POSIX :: Linux
Classifier: Operating System :: MacOS
Requires-Python: >=3.9
License-File: LICENSE
Requires-Dist: beaker-py~=2.0
Requires-Dist: PyYAML~=6.0
Requires-Dist: fabric~=3.2
Requires-Dist: pandas~=2.3
Requires-Dist: tabulate<1.0.0,>=0.9.0
Dynamic: author
Dynamic: author-email
Dynamic: classifier
Dynamic: description
Dynamic: description-content-type
Dynamic: home-page
Dynamic: license
Dynamic: license-file
Dynamic: project-url
Dynamic: requires-dist
Dynamic: requires-python
Dynamic: summary
